hlagenie/__init__.py
hlagenie/configs.py
hlagenie/data_repository.py
hlagenie/db.py
hlagenie/genie.py
hlagenie/load.py
hlagenie/misc.py
hlagenie/smart_sort.py
hlagenie-0.4.5.data/scripts/hlagenie
hlagenie-0.4.5.data/scripts/hlagenie-match
hlagenie-0.4.5.dist-info/LICENSE
hlagenie-0.4.5.dist-info/METADATA
hlagenie-0.4.5.dist-info/WHEEL
hlagenie-0.4.5.dist-info/top_level.txt
hlagenie-0.4.5.dist-info/RECORD
