Metadata-Version: 2.1
Name: hlagenie
Version: 0.4.5
Summary: Sequence handing for HLA with Python
Home-page: https://github.com/gbiagini/hlagenie
Author: Giovanni Biagini
Author-email: dbiagini@tulane.edu
License: LGPL 3.0
Keywords: hlagenie
Classifier: Development Status :: 3 - Alpha
Classifier: Intended Audience :: Science/Research
Classifier: Topic :: Scientific/Engineering :: Bio-Informatics
Classifier: License :: OSI Approved :: GNU Lesser General Public License v3 (LGPLv3)
Classifier: Natural Language :: English
Classifier: Programming Language :: Python :: 3.11
Provides: hlagenie
License-File: LICENSE
Requires-Dist: biopython >=1.81
Requires-Dist: requests >=2.31.0
Requires-Dist: toml >=0.10.2
Requires-Dist: py-ard >=1.0.0
